Flask_JSONSchema_Ext-0.1.2.dist-info/DESCRIPTION.rst
Flask_JSONSchema_Ext-0.1.2.dist-info/METADATA
Flask_JSONSchema_Ext-0.1.2.dist-info/RECORD
Flask_JSONSchema_Ext-0.1.2.dist-info/WHEEL
Flask_JSONSchema_Ext-0.1.2.dist-info/metadata.json
Flask_JSONSchema_Ext-0.1.2.dist-info/top_level.txt
flask_jsonschema_ext/__init__.py
flask_jsonschema_ext/core.py
