Metadata-Version: 2.0
Name: Flask-JSONSchema-Ext
Version: 0.1.2
Summary: Flask JSONSchema Extended Library
Home-page: https://github.com/rachekalmir/flask-jsonschema-ext
Author: rachekalmir
Author-email: rachekalmir@users.noreply.github.com
License: MIT
Platform: UNKNOWN
Classifier: Development Status :: 4 - Beta
Classifier: Environment :: Web Environment
Classifier: Intended Audience :: Developers
Classifier: License :: OSI Approved :: MIT License
Classifier: Operating System :: OS Independent
Classifier: Programming Language :: Python :: 3
Classifier: Programming Language :: Python :: 3.3
Classifier: Programming Language :: Python :: 3.4
Classifier: Programming Language :: Python :: 3.5
Classifier: Programming Language :: Python :: 3.6
Classifier: Topic :: Internet :: WWW/HTTP :: Dynamic Content
Classifier: Topic :: Software Development :: Libraries :: Python Modules
Requires-Dist: flask (>=0.11.0)
Requires-Dist: jsonschema (>=2.6.0)
Requires-Dist: sqlalchemy (>=1.0.0)
